mseep_shopify_py_mcp-0.1.6.dist-info/licenses/LICENSE
shopify_py_mcp/__init__.py
shopify_py_mcp/server.py
mseep_shopify_py_mcp-0.1.6.dist-info/METADATA
mseep_shopify_py_mcp-0.1.6.dist-info/WHEEL
mseep_shopify_py_mcp-0.1.6.dist-info/entry_points.txt
mseep_shopify_py_mcp-0.1.6.dist-info/top_level.txt
mseep_shopify_py_mcp-0.1.6.dist-info/RECORD
